{"type":"PR","pr":{"number":71,"head":"2b4a56a9d672e81b1b0f14d23b41b8b2ed9dc43a"},"user":"Tatiana Corallo-Jackson","status":"pending_publish","branch":"cms/news/news1/index.fr","collection":"news","commitMessage":"Update article “news1/index.fr”","title":"Tessi aux Quadient Inspire Days 2019 \"Delight Customer. Be Digital.\"","description":"No Description!","objects":{"entry":{"path":"src/data/news/news1/index.fr.md","sha":"aebab8873687eacf8d0c64d31a32d96bdc484d14"},"files":[]},"timeStamp":"2019-12-27T09:43:15.164Z","version":"1"}